rss_reader/__init__.py
rss_reader/__main__.py
rss_reader/argument_parser/__init__.py
rss_reader/argument_parser/_models.py
rss_reader/argument_parser/_parser.py
rss_reader/argument_parser/types.py
rss_reader/config/__init__.py
rss_reader/config/_base.py
rss_reader/config/_data.py
rss_reader/converter/__init__.py
rss_reader/converter/_converter.py
rss_reader/converter/html_template.jinja2
rss_reader/converter/pretty_html_template.jinja2
rss_reader/converter/xhtml_template.jinja2
rss_reader/imports/__init__.py
rss_reader/imports/_json.py
rss_reader/printer/__init__.py
rss_reader/printer/_printer.py
rss_reader/reader/__init__.py
rss_reader/reader/_reader.py
rss_reader-3.5.1.dist-info/entry_points.txt
rss_reader-3.5.1.dist-info/LICENSE
rss_reader-3.5.1.dist-info/WHEEL
rss_reader-3.5.1.dist-info/METADATA
rss_reader-3.5.1.dist-info/RECORD
