Metadata-Version: 2.1
Name: rss-reader
Version: 3.5.1
Summary: A simple CLI rss reader
License: GPLv3
Keywords: python,python3,cli,rss,reader,gplv3,typed,typed-python
Author: dhvcc
Author-email: 1337kwiz@gmail.com
Requires-Python: >=3.7,<4.0
Classifier: Development Status :: 5 - Production/Stable
Classifier: Intended Audience :: Developers
Classifier: Intended Audience :: End Users/Desktop
Classifier: License :: OSI Approved :: MIT License
Classifier: License :: Other/Proprietary License
Classifier: Natural Language :: English
Classifier: Operating System :: OS Independent
Classifier: Programming Language :: Python :: 3
Classifier: Programming Language :: Python :: 3.10
Classifier: Programming Language :: Python :: 3.7
Classifier: Programming Language :: Python :: 3.8
Classifier: Programming Language :: Python :: 3.9
Classifier: Typing :: Typed
Provides-Extra: speedups
Requires-Dist: Jinja2
Requires-Dist: colorama (>=0.4.3,<0.5.0)
Requires-Dist: ebooklib (>=0.17.1,<0.18.0)
Requires-Dist: pathvalidate (>=2.4.1,<3.0.0)
Requires-Dist: pydantic
Requires-Dist: requests
Requires-Dist: rss-parser (>=0.2.3,<0.3.0)
Requires-Dist: weasyprint (>=51,<52)
Project-URL: Bug Tracker, https://github.com/dhvcc/rss-reader/issues
Project-URL: Homepage, https://dhvcc.github.io/rss-reader
Project-URL: Source, https://github.com/dhvcc/rss-reader
